cloneui/__init__.py
cloneui/cloneui.py
cloneui-0.1.2.dist-info/METADATA
cloneui-0.1.2.dist-info/WHEEL
cloneui-0.1.2.dist-info/top_level.txt
cloneui-0.1.2.dist-info/RECORD
