Metadata-Version: 2.1
Name: cloneui
Version: 0.1.2
Summary: CloneUI is a Python library designed to clone a webpage into a structured folder format effortlessly.
Home-page: https://github.com/yourusername/cloneui
Author: Dhruv Ahir
Author-email: incnogeto@gmail.com
License: MIT
Classifier: Programming Language :: Python :: 3
Classifier: License :: OSI Approved :: MIT License
Classifier: Operating System :: OS Independent
Requires-Dist: requests
Requires-Dist: beautifulsoup4
